<?xml version="1.0" encoding="utf-8"?>
<world>
 <worldbody>
  <geom euler="0 0 0" material="mat_floor_001" name="floor" pos="0 0 0" size="3.5 3.5 0.5" type="plane"/>
  <geom euler="90 180 0" material="mat_wall_001" name="wall_1" pos="0 3.5 3.5" size="3.5 3.5 0.5" type="plane"/>
  <geom euler="270 0 90" material="mat_wall_001" name="wall_2" pos="3.5 0 3.5" size="3.5 3.5 0.5" type="plane"/>
  <geom euler="-90 180 0" material="mat_wall_001" name="wall_3" pos="0 -3.5 3.5" size="3.5 3.5 0.5" type="plane"/>
  <geom euler="270 0 -90" material="mat_wall_001" name="wall_4" pos="-3.5 0 3.5" size="3.5 3.5 0.5" type="plane"/>
  <body euler="0 0 153" pos="0.19270991603209026 0.16457727622847168 0.46112457308369037">
   <freejoint/>
   <geom condim="6" density="20" euler="0 0 0" friction="1 0.01 0.1" name="shape_3" pos="0 0 0" rgba="1 0 0 1" size="0.11651250597035478 0.09859331529717716 0.09549753999763233" type="box"/>
   <body>
    <site name="sensor_site_velo_collapse" pos="0 0 0" size="0.01"/>
   </body>
  </body>
  <body euler="0 0 360" pos="0.18656549189838442 0.15975608340501019 0.26671158098804176">
   <freejoint/>
   <geom condim="6" density="20" euler="0 0 0" friction="1 0.01 0.1" name="shape_2" pos="0 0 0" rgba="0 0 1 1" size="0.09965734755964079 0.11943060551913959 0.09891545209801628" type="box"/>
  </body>
  <body euler="0 0 187" pos="0.19608490471401513 0.16368068625069543 0.08389806444501269">
   <freejoint/>
   <geom condim="6" density="20" euler="0 0 0" friction="1 0.01 0.1" name="shape_1" pos="0 0 0" rgba="1 0 1 1" size="0.07961988273692745 0.11826562933788487 0.08389806444501277" type="box"/>
  </body>
  <light castshadow="false" dir="0 0 -20" directional="true" mode="fixed" name="light_0" pos="0 0 20"/>
  <light castshadow="false" dir="9 9 -20" directional="true" mode="fixed" name="light_1" pos="-9 -9 20"/>
  <light castshadow="false" dir="9 -9 -20" directional="true" mode="fixed" name="light_2" pos="-9 9 20"/>
  <light castshadow="false" dir="-9 -9 -20" directional="true" mode="fixed" name="light_3" pos="9 9 20"/>
  <light castshadow="false" dir="-9 9 -20" directional="true" mode="fixed" name="light_4" pos="9 -9 20"/>
  <camera euler="58.0000016589622 -7.058926240594811e-07 -144.00000085027406" fovy="45" mode="fixed" name="cam_1" pos="-1.121557869349777 1.543691974135203 1.192318344524711"/>
  <camera euler="82.00000147714735 7.172983857582399e-07 150.0000001331201" fovy="45" mode="fixed" name="cam_2" pos="1.1140515773342665 1.9295939341951984 0.31313947716014723"/>
  <camera euler="34.000003178123066 -1.5873111554358256e-07 14.999999871686544" fovy="45" mode="fixed" name="cam_3" pos="0.325641989934911 -1.2153124515149194 1.865334538248844"/>
  <camera euler="51.00000214125817 -3.17807919214384e-07 -23.999998746713693" fovy="45" mode="fixed" name="cam_4" pos="-0.711210913971578 -1.597405866782192 1.4159708798621342"/>
  <camera euler="20.000000445396637 2.081718457338723e-07 90.9999993142628" fovy="45" mode="fixed" name="cam_5" pos="0.7694281170027643 0.013430417739879514 2.1143083967682936"/>
 </worldbody>
 <sensor>
  <velocimeter name="velo_collapse" site="sensor_site_velo_collapse"/>
 </sensor>
</world>