<?xml version="1.0" encoding="utf-8"?>
<world>
 <worldbody>
  <geom euler="0 0 0" material="mat_floor_001" name="floor" pos="0 0 0" size="10 10 0.5" type="plane"/>
  <geom euler="90 180 0" material="mat_wall_001" name="wall_1" pos="0 10 10" size="10 10 0.5" type="plane"/>
  <geom euler="270 0 90" material="mat_wall_001" name="wall_2" pos="10 0 10" size="10 10 0.5" type="plane"/>
  <geom euler="-90 180 0" material="mat_wall_001" name="wall_3" pos="0 -10 10" size="10 10 0.5" type="plane"/>
  <geom euler="270 0 -90" material="mat_wall_001" name="wall_4" pos="-10 0 10" size="10 10 0.5" type="plane"/>
  <body euler="0 0 110" pos="-0.26241319615651093 0.13070003824534326 1.927157849686997">
   <freejoint/>
   <geom condim="6" density="20" euler="0 0 0" friction="1 0.01 0.1" name="shape_4" pos="0 0 0" rgba="1 0 1 1" size="0.2904819236928609 0.3084896086770343 0.2613366987781355" type="box"/>
   <body>
    <site name="sensor_site_velo_collapse" pos="0 0 0" size="0.01"/>
   </body>
  </body>
  <body pos="-0.24184978399796564 0.13459175916531768 1.383594885292074">
   <freejoint/>
   <geom condim="6" density="20" euler="0 0 0" friction="1 0.01 0.1" name="shape_3" pos="0 0 0" rgba="0 0 1 1" size="0.28860316408009745 0.28222626561678726" type="cylinder"/>
  </body>
  <body pos="-0.3122986864857199 0.19483895041946192 0.8146978138771455">
   <freejoint/>
   <geom condim="6" density="20" euler="0 0 0" friction="1 0.01 0.1" name="shape_2" pos="0 0 0" rgba="1 0 0 1" size="0.31286411003513254 0.28667080579814147" type="cylinder"/>
  </body>
  <body pos="-0.2125970632842569 0.19977871445089124 0.26401350403950197">
   <freejoint/>
   <geom condim="6" density="20" euler="0 0 0" friction="1 0.01 0.1" name="shape_1" pos="0 0 0" rgba="0 1 1 1" size="0.25045408537548935 0.2640135040395019" type="cylinder"/>
  </body>
  <light castshadow="false" dir="0 0 -20" directional="true" mode="fixed" name="light_0" pos="0 0 20"/>
  <light castshadow="false" dir="9 9 -20" directional="true" mode="fixed" name="light_1" pos="-9 -9 20"/>
  <light castshadow="false" dir="9 -9 -20" directional="true" mode="fixed" name="light_2" pos="-9 9 20"/>
  <light castshadow="false" dir="-9 -9 -20" directional="true" mode="fixed" name="light_3" pos="9 9 20"/>
  <light castshadow="false" dir="-9 9 -20" directional="true" mode="fixed" name="light_4" pos="9 -9 20"/>
  <camera euler="22.999997999488503 1.9538858580257159e-07 161.99999769225448" fovy="45" mode="fixed" name="cam_1" pos="0.7848266330741638 2.4154480081490375 5.983281547440862"/>
  <camera euler="38.99999981934006 3.677537850991838e-07 145.9999969275249" fovy="45" mode="fixed" name="cam_2" pos="2.287424728449279 3.391246620809754 5.05144874947031"/>
  <camera euler="73.00000088624317 2.5499728214290693e-07 102.00000012358026" fovy="45" mode="fixed" name="cam_3" pos="6.080146817001208 1.2923751018707068 1.900416080697789"/>
 </worldbody>
 <sensor>
  <velocimeter name="velo_collapse" site="sensor_site_velo_collapse"/>
 </sensor>
</world>