<?xml version="1.0" encoding="utf-8"?>
<world>
 <worldbody>
  <geom euler="0 0 0" material="mat_floor_001" name="floor" pos="0 0 0" size="3.5 3.5 0.5" type="plane"/>
  <geom euler="90 180 0" material="mat_wall_001" name="wall_1" pos="0 3.5 3.5" size="3.5 3.5 0.5" type="plane"/>
  <geom euler="270 0 90" material="mat_wall_001" name="wall_2" pos="3.5 0 3.5" size="3.5 3.5 0.5" type="plane"/>
  <geom euler="-90 180 0" material="mat_wall_001" name="wall_3" pos="0 -3.5 3.5" size="3.5 3.5 0.5" type="plane"/>
  <geom euler="270 0 -90" material="mat_wall_001" name="wall_4" pos="-3.5 0 3.5" size="3.5 3.5 0.5" type="plane"/>
  <body euler="0 0 35" pos="0.2640307242574415 0.07728701805734706 0.7327011731639436">
   <freejoint/>
   <geom condim="6" density="20" euler="0 0 0" friction="1 0.01 0.1" name="shape_4" pos="0 0 0" rgba="0 0 1 1" size="0.08579665672575952 0.08732563598080698 0.11500696952646594" type="box"/>
   <body>
    <site name="sensor_site_velo_collapse" pos="0 0 0" size="0.01"/>
   </body>
  </body>
  <body euler="0 0 172" pos="0.45400278498121105 0.20651698609816843 0.5036942711071029">
   <freejoint/>
   <geom condim="6" density="20" euler="0 0 0" friction="1 0.01 0.1" name="shape_3" pos="0 0 0" rgba="0 1 0 1" size="0.12013793029857234 0.10441131166201986 0.11399993253037483" type="box"/>
  </body>
  <body euler="0 0 337" pos="0.3776240755158074 0.1520692274835382 0.3078897422552449">
   <freejoint/>
   <geom condim="6" density="20" euler="0 0 0" friction="1 0.01 0.1" name="shape_2" pos="0 0 0" rgba="1 1 0 1" size="0.08955536984834583 0.08250701206625032 0.0818045963214831" type="box"/>
  </body>
  <body euler="0 0 280" pos="0.37247594132361905 0.15386323497648263 0.11304257296688092">
   <freejoint/>
   <geom condim="6" density="20" euler="0 0 0" friction="1 0.01 0.1" name="shape_1" pos="0 0 0" rgba="0 1 1 1" size="0.08125218973953606 0.1020523076213087 0.11304257296688085" type="box"/>
  </body>
  <light castshadow="false" dir="0 0 -20" directional="true" mode="fixed" name="light_0" pos="0 0 20"/>
  <light castshadow="false" dir="9 9 -20" directional="true" mode="fixed" name="light_1" pos="-9 -9 20"/>
  <light castshadow="false" dir="9 -9 -20" directional="true" mode="fixed" name="light_2" pos="-9 9 20"/>
  <light castshadow="false" dir="-9 -9 -20" directional="true" mode="fixed" name="light_3" pos="9 9 20"/>
  <light castshadow="false" dir="-9 9 -20" directional="true" mode="fixed" name="light_4" pos="9 -9 20"/>
  <camera euler="9.000000029659525 1.2528599279065293e-08 7.999999073724772" fovy="45" mode="fixed" name="cam_1" pos="0.0489858065925252 -0.3485521250550229 2.22229876633906"/>
  <camera euler="78.00000071497806 3.211959732832662e-07 -13.000000008037743" fovy="45" mode="fixed" name="cam_2" pos="-0.49507950170023085 -2.1444249174671715 0.4678013043399585"/>
  <camera euler="8.000000597890512 -4.735438809699949e-08 8.999999437611715" fovy="45" mode="fixed" name="cam_3" pos="0.048985806592525265 -0.30928421057113487 2.2281031546685335"/>
  <camera euler="63.00000125050002 9.932393151453346e-07 -52.00000050294662" fovy="45" mode="fixed" name="cam_4" pos="-1.579776125836909 -1.234256380214844 1.0214786244139804"/>
  <camera euler="62.999999582271606 -6.160918508499796e-07 -110.99999715933552" fovy="45" mode="fixed" name="cam_5" pos="-1.871609064443023 0.7184434074859584 1.0214786244139804"/>
 </worldbody>
 <sensor>
  <velocimeter name="velo_collapse" site="sensor_site_velo_collapse"/>
 </sensor>
</world>