<?xml version="1.0" encoding="utf-8"?>
<world>
 <worldbody>
  <geom euler="0 0 0" material="mat_floor_001" name="floor" pos="0 0 0" size="20 20 0.5" type="plane"/>
  <geom euler="90 180 0" material="mat_wall_001" name="wall_1" pos="0 20 20" size="20 20 0.5" type="plane"/>
  <geom euler="270 0 90" material="mat_wall_001" name="wall_2" pos="20 0 20" size="20 20 0.5" type="plane"/>
  <geom euler="-90 180 0" material="mat_wall_001" name="wall_3" pos="0 -20 20" size="20 20 0.5" type="plane"/>
  <geom euler="270 0 -90" material="mat_wall_001" name="wall_4" pos="-20 0 20" size="20 20 0.5" type="plane"/>
  <body euler="0 0 163" pos="0.47421405662835614 -2.192453483110279 0.31088341711521644">
   <freejoint/>
   <geom condim="6" density="20" euler="0 0 0" friction="1 0.01 0.1" name="shape_4" pos="0 0 0" rgba="0 1 0 1" size="0.4450193813370326 0.4950614491851292 0.31088341711521644" type="box"/>
   <body>
    <site name="sensor_site_velo_collapse" pos="0 0 0" size="0.01"/>
   </body>
  </body>
  <body euler="0 0 23" pos="0.6377209495047125 0.957194732835827 0.4619361651693574">
   <freejoint/>
   <geom condim="6" density="20" euler="0 0 0" friction="1 0.01 0.1" name="shape_3" pos="0 0 0" rgba="1 1 0 1" size="0.4813875149340163 0.37983127855260834 0.4619361651693574" type="box"/>
  </body>
  <body euler="0 0 71" pos="-1.6498581594755506 1.241168560080339 0.3030231324865194">
   <freejoint/>
   <geom condim="6" density="20" euler="0 0 0" friction="1 0.01 0.1" name="shape_2" pos="0 0 0" rgba="1 0 1 1" size="0.3893998339968698 0.3984364755022246 0.3030231324865194" type="box"/>
  </body>
  <body euler="0 0 150" pos="0.18723264023649477 2.341551197476292 0.36195098327837916">
   <freejoint/>
   <geom condim="6" density="20" euler="0 0 0" friction="1 0.01 0.1" name="shape_1" pos="0 0 0" rgba="0 0 1 1" size="0.2824977775050158 0.3697351691643507 0.36195098327837916" type="box"/>
  </body>
  <light castshadow="false" dir="0 0 -20" directional="true" mode="fixed" name="light_0" pos="0 0 20"/>
  <light castshadow="false" dir="9 9 -20" directional="true" mode="fixed" name="light_1" pos="-9 -9 20"/>
  <light castshadow="false" dir="9 -9 -20" directional="true" mode="fixed" name="light_2" pos="-9 9 20"/>
  <light castshadow="false" dir="-9 -9 -20" directional="true" mode="fixed" name="light_3" pos="9 9 20"/>
  <light castshadow="false" dir="-9 9 -20" directional="true" mode="fixed" name="light_4" pos="9 -9 20"/>
  <camera euler="70.3461758562914 -8.73531824432688e-07 -99.00000287566954" fovy="45" mode="fixed" name="cam_1" pos="-6.913818384165964 1.0950412552816147 4.0"/>
  <camera euler="70.34617550104456 1.979306403150657e-06 113.9999993366627" fovy="45" mode="fixed" name="cam_2" pos="6.394818203498206 2.8471565015306015 4.0"/>
  <camera euler="70.34617768691544 -3.657222376019458e-07 120.0000008921742" fovy="45" mode="fixed" name="cam_3" pos="6.06217782649107 3.500000000000001 4.0"/>
 </worldbody>
 <sensor>
  <velocimeter name="velo_collapse" site="sensor_site_velo_collapse"/>
 </sensor>
</world>