<?xml version="1.0" encoding="utf-8"?>
<world>
 <worldbody>
  <geom euler="0 0 0" material="mat_floor_001" name="floor" pos="0 0 0" size="10 10 0.5" type="plane"/>
  <geom euler="90 180 0" material="mat_wall_001" name="wall_1" pos="0 10 10" size="10 10 0.5" type="plane"/>
  <geom euler="270 0 90" material="mat_wall_001" name="wall_2" pos="10 0 10" size="10 10 0.5" type="plane"/>
  <geom euler="-90 180 0" material="mat_wall_001" name="wall_3" pos="0 -10 10" size="10 10 0.5" type="plane"/>
  <geom euler="270 0 -90" material="mat_wall_001" name="wall_4" pos="-10 0 10" size="10 10 0.5" type="plane"/>
  <body euler="0 0 160" pos="1.523966432932537 0.08173093560529843 0.31444733730893315">
   <freejoint/>
   <geom condim="6" density="20" euler="0 0 0" friction="1 0.01 0.1" name="shape_4" pos="0 0 0" rgba="1 0 0 1" size="0.295544833407308 0.34854060784810226 0.31444733730893315" type="box"/>
   <body>
    <site name="sensor_site_velo_collapse" pos="0 0 0" size="0.01"/>
   </body>
  </body>
  <body euler="0 0 149" pos="-0.03711460865168137 -1.4178857613109637 0.33940839113724564">
   <freejoint/>
   <geom condim="6" density="20" euler="0 0 0" friction="1 0.01 0.1" name="shape_3" pos="0 0 0" rgba="1 0 1 1" size="0.3385445577404942 0.2712654766709333 0.33940839113724564" type="box"/>
  </body>
  <body euler="0 0 298" pos="-1.9793118024720222 0.5969298919311314 0.26921388673490687">
   <freejoint/>
   <geom condim="6" density="20" euler="0 0 0" friction="1 0.01 0.1" name="shape_2" pos="0 0 0" rgba="0 1 1 1" size="0.2782263930191708 0.30251338999168725 0.26921388673490687" type="box"/>
  </body>
  <body euler="0 0 134" pos="0.5548543427124608 1.3749428338688237 0.2948748475015844">
   <freejoint/>
   <geom condim="6" density="20" euler="0 0 0" friction="1 0.01 0.1" name="shape_1" pos="0 0 0" rgba="0 1 0 1" size="0.3180353510308794 0.31343789165037717 0.2948748475015844" type="box"/>
  </body>
  <light castshadow="false" dir="0 0 -20" directional="true" mode="fixed" name="light_0" pos="0 0 20"/>
  <light castshadow="false" dir="9 9 -20" directional="true" mode="fixed" name="light_1" pos="-9 -9 20"/>
  <light castshadow="false" dir="9 -9 -20" directional="true" mode="fixed" name="light_2" pos="-9 9 20"/>
  <light castshadow="false" dir="-9 -9 -20" directional="true" mode="fixed" name="light_3" pos="9 9 20"/>
  <light castshadow="false" dir="-9 9 -20" directional="true" mode="fixed" name="light_4" pos="9 -9 20"/>
  <camera euler="58.99999887228318 -1.1217021222851459e-06 72.00000000769361" fovy="45" mode="fixed" name="cam_1" pos="5.298894554771164 -1.7217152091064474 3.347747486915352"/>
  <camera euler="67.00000046957075 2.36813682084637e-07 -55.00000019899973" fovy="45" mode="fixed" name="cam_2" pos="-4.901217311142784 -3.4318693076661027 2.5397523351802795"/>
  <camera euler="12.000000130970882 -3.300832827297112e-07 33.00000276256328" fovy="45" mode="fixed" name="cam_3" pos="0.7360393472596269 -1.133401202834054 6.357959404769736"/>
 </worldbody>
 <sensor>
  <velocimeter name="velo_collapse" site="sensor_site_velo_collapse"/>
 </sensor>
</world>