<?xml version="1.0" encoding="utf-8"?>
<world>
 <worldbody>
  <geom euler="0 0 0" material="mat_floor_001" name="floor" pos="0 0 0" size="10 10 0.5" type="plane"/>
  <geom euler="90 180 0" material="mat_wall_001" name="wall_1" pos="0 10 10" size="10 10 0.5" type="plane"/>
  <geom euler="270 0 90" material="mat_wall_001" name="wall_2" pos="10 0 10" size="10 10 0.5" type="plane"/>
  <geom euler="-90 180 0" material="mat_wall_001" name="wall_3" pos="0 -10 10" size="10 10 0.5" type="plane"/>
  <geom euler="270 0 -90" material="mat_wall_001" name="wall_4" pos="-10 0 10" size="10 10 0.5" type="plane"/>
  <body euler="0 0 92" pos="-1.2536214678489275 1.9857069435028034 0.33685291347758595">
   <freejoint/>
   <geom condim="6" density="20" euler="0 0 0" friction="1 0.01 0.1" name="shape_4" pos="0 0 0" rgba="1 0 1 1" size="0.2725037107294799 0.33138528079059004 0.33685291347758595" type="box"/>
   <body>
    <site name="sensor_site_velo_collapse" pos="0 0 0" size="0.01"/>
   </body>
  </body>
  <body euler="0 0 312" pos="0.9693929239462094 -1.9978395434699547 0.3195156511208054">
   <freejoint/>
   <geom condim="6" density="20" euler="0 0 0" friction="1 0.01 0.1" name="shape_3" pos="0 0 0" rgba="1 0 0 1" size="0.33451883906551977 0.3349429711278762 0.3195156511208054" type="box"/>
  </body>
  <body pos="-0.45818433526156577 -1.6220132132014164 0.34888720789716676">
   <freejoint/>
   <geom condim="6" density="20" euler="0 0 0" friction="1 0.01 0.1" name="shape_2" pos="0 0 0" rgba="0 1 0 1" size="0.3491981218743033 0.34888720789716676" type="cylinder"/>
  </body>
  <body euler="0 0 5" pos="-0.40898153236489554 -1.7520795555475321 0.3107901723648775">
   <freejoint/>
   <geom condim="6" density="20" euler="0 0 0" friction="1 0.01 0.1" name="shape_1" pos="0 0 0" rgba="0 1 1 1" size="0.25270245850491485 0.30313945819984883 0.3107901723648775" type="box"/>
  </body>
  <light castshadow="false" dir="0 0 -20" directional="true" mode="fixed" name="light_0" pos="0 0 20"/>
  <light castshadow="false" dir="9 9 -20" directional="true" mode="fixed" name="light_1" pos="-9 -9 20"/>
  <light castshadow="false" dir="9 -9 -20" directional="true" mode="fixed" name="light_2" pos="-9 9 20"/>
  <light castshadow="false" dir="-9 -9 -20" directional="true" mode="fixed" name="light_3" pos="9 9 20"/>
  <light castshadow="false" dir="-9 9 -20" directional="true" mode="fixed" name="light_4" pos="9 -9 20"/>
  <camera euler="64.00000179018707 8.981462261680651e-07 -141.00000224516182" fovy="45" mode="fixed" name="cam_1" pos="-3.6765912344866734 4.540212061209288 2.8494124541290025"/>
  <camera euler="2.0000000820853305 4.6140968319364984e-08 126.9999991469068" fovy="45" mode="fixed" name="cam_2" pos="0.18116785277107247 0.1365197692040684 6.496040375624123"/>
  <camera euler="67.00000027536159 4.5872644004217995e-07 111.99999931588167" fovy="45" mode="fixed" name="cam_3" pos="5.547602048114551 2.2413767179351076 2.5397523351802795"/>
 </worldbody>
 <sensor>
  <velocimeter name="velo_collapse" site="sensor_site_velo_collapse"/>
 </sensor>
</world>