<?xml version="1.0" encoding="utf-8"?>
<world>
 <worldbody>
  <geom euler="0 0 0" material="mat_floor_001" name="floor" pos="0 0 0" size="3 3 0.5" type="plane"/>
  <body euler="0 0 231" pos="-0.5501020252204737 -0.48104419959934536 0.06948510407900524">
   <freejoint/>
   <geom condim="6" density="20" euler="0 0 0" friction="1 0.01 0.1" name="shape_4" pos="0 0 0" rgba="0 1 1 1" size="0.06282905843147206 0.05661176752699957 0.06948510407900524" type="box"/>
   <body>
    <site name="sensor_site_velo_collapse" pos="0 0 0" size="0.01"/>
   </body>
  </body>
  <body euler="0 0 93" pos="-0.36964873779605634 0.07534067988121007 0.06464885054027131">
   <freejoint/>
   <geom condim="6" density="20" euler="0 0 0" friction="1 0.01 0.1" name="shape_3" pos="0 0 0" rgba="1 0 0 1" size="0.06759457668998549 0.05008771980499042 0.06464885054027131" type="box"/>
  </body>
  <body euler="0 0 313" pos="-0.00682232438167929 0.45847529196926196 0.07152655539912187">
   <freejoint/>
   <geom condim="6" density="20" euler="0 0 0" friction="1 0.01 0.1" name="shape_2" pos="0 0 0" rgba="1 0 1 1" size="0.05291337973463005 0.07233467098992903 0.07152655539912187" type="box"/>
  </body>
  <body euler="0 0 152" pos="0.03321267040508191 0.21145650821224993 0.05745892979197072">
   <freejoint/>
   <geom condim="6" density="20" euler="0 0 0" friction="1 0.01 0.1" name="shape_1" pos="0 0 0" rgba="0 1 0 1" size="0.05473484213103016 0.06273592177223507 0.05745892979197072" type="box"/>
  </body>
  <light castshadow="false" dir="0 0 -20" directional="true" mode="fixed" name="light_0" pos="0 0 20"/>
  <light castshadow="false" dir="9 9 -20" directional="true" mode="fixed" name="light_1" pos="-9 -9 20"/>
  <light castshadow="false" dir="9 -9 -20" directional="true" mode="fixed" name="light_2" pos="-9 9 20"/>
  <light castshadow="false" dir="-9 -9 -20" directional="true" mode="fixed" name="light_3" pos="9 9 20"/>
  <light castshadow="false" dir="-9 9 -20" directional="true" mode="fixed" name="light_4" pos="9 -9 20"/>
  <camera euler="31.58826563795311 7.498310328174951e-09 169.8129426044941" fovy="45" mode="fixed" name="cam_1" pos="0.18528511363350042 1.0311077143540441 1.7036684853766004"/>
  <camera euler="12.413793077489673 0.0 -89.99999999999994" fovy="45" mode="fixed" name="cam_2" pos="-0.42994088042204703 -4.898587196589413e-16 1.9532411114201735"/>
  <camera euler="64.84199713978714 1.3372182886117352e-07 -62.36129057716939" fovy="45" mode="fixed" name="cam_3" pos="-1.6037076290448893 -0.8397782031205299 0.85023197429106"/>
 </worldbody>
 <sensor>
  <velocimeter name="velo_collapse" site="sensor_site_velo_collapse"/>
 </sensor>
</world>