<?xml version="1.0" encoding="utf-8"?>
<world>
 <worldbody>
  <geom euler="0 0 0" material="mat_floor_001" name="floor" pos="0 0 0" size="100 100 0.5" type="plane"/>
  <body pos="0.529102792279287 -1.0240795717718254 3.839436635421767">
   <freejoint/>
   <geom condim="6" euler="0 0 0" friction="1 0.01 0.01" name="shape_6" pos="0 0 0" rgba="0 0 1 1" size="0.39350600146591164 0.30081293574931234" type="cylinder"/>
   <body>
    <site name="sensor_site_velo_collapse" pos="0 0 0" size="0.01"/>
   </body>
  </body>
  <body pos="0.49257272980471556 -1.106199376720222 3.0882754907472396">
   <freejoint/>
   <geom condim="6" euler="0 0 0" friction="1 0.01 0.01" name="shape_5" pos="0 0 0" rgba="1 0 1 1" size="0.4995331483580286 0.45034820892521477" type="cylinder"/>
  </body>
  <body pos="0.47644989055055265 -0.894512902587647 2.3270339131768987">
   <freejoint/>
   <geom condim="6" euler="0 0 0" friction="1 0.01 0.01" name="shape_4" pos="0 0 0" rgba="0 1 1 1" size="0.2752449486213957 0.3108933686451262" type="cylinder"/>
  </body>
  <body pos="0.4210587508498891 -1.0910446260564455 1.7508344036312629">
   <freejoint/>
   <geom condim="6" euler="0 0 0" friction="1 0.01 0.01" name="shape_3" pos="0 0 0" rgba="1 1 0 1" size="0.4251634922884798 0.26530614090050963" type="cylinder"/>
  </body>
  <body pos="0.39930081354269176 -1.143514269197691 1.125247122944668">
   <freejoint/>
   <geom condim="6" euler="0 0 0" friction="1 0.01 0.01" name="shape_2" pos="0 0 0" rgba="1 0 0 1" size="0.3449631525209748 0.3602811397860851" type="cylinder"/>
  </body>
  <body pos="0.5184664683332284 -1.0838109630116974 0.38248299157929155">
   <freejoint/>
   <geom condim="6" euler="0 0 0" friction="1 0.01 0.01" name="shape_1" pos="0 0 0" rgba="0 1 0 1" size="0.2921007336104363 0.38248299157929155" type="cylinder"/>
  </body>
  <light castshadow="false" dir="0 0 -20" directional="true" mode="fixed" name="light_0" pos="0 0 20"/>
  <light castshadow="false" dir="9 9 -20" directional="true" mode="fixed" name="light_1" pos="-9 -9 20"/>
  <light castshadow="false" dir="9 -9 -20" directional="true" mode="fixed" name="light_2" pos="-9 9 20"/>
  <light castshadow="false" dir="-9 -9 -20" directional="true" mode="fixed" name="light_3" pos="9 9 20"/>
  <light castshadow="false" dir="-9 9 -20" directional="true" mode="fixed" name="light_4" pos="9 -9 20"/>
  <camera euler="75 0 -45" fovy="45" mode="fixed" name="cam_1" pos="-7 -7 5"/>
  <camera euler="75 0 -75" fovy="45" mode="fixed" name="cam_2" pos="-9 -2 5"/>
  <camera euler="75 0 -15" fovy="45" mode="fixed" name="cam_3" pos="-2 -9 5"/>
  <camera euler="75 0 225" fovy="45" mode="fixed" name="cam_4" pos="-7 7 5"/>
  <camera euler="75 0 255" fovy="45" mode="fixed" name="cam_5" pos="-9 2 5"/>
  <camera euler="75 0 195" fovy="45" mode="fixed" name="cam_6" pos="-2 9 5"/>
  <camera euler="75 0 135" fovy="45" mode="fixed" name="cam_7" pos="7 7 5"/>
  <camera euler="75 0 105" fovy="45" mode="fixed" name="cam_8" pos="9 2 5"/>
  <camera euler="75 0 165" fovy="45" mode="fixed" name="cam_9" pos="2 9 5"/>
  <camera euler="75 0 45" fovy="45" mode="fixed" name="cam_10" pos="7 -7 5"/>
  <camera euler="75 0 75" fovy="45" mode="fixed" name="cam_11" pos="9 -2 5"/>
  <camera euler="75 0 15" fovy="45" mode="fixed" name="cam_12" pos="2 -9 5"/>
  <camera euler="45 0 -45" fovy="45" mode="fixed" name="cam_13" pos="-5 -5 9"/>
  <camera euler="45 0 225" fovy="45" mode="fixed" name="cam_14" pos="-5 5 9"/>
  <camera euler="45 0 135" fovy="45" mode="fixed" name="cam_15" pos="5 5 9"/>
  <camera euler="45 0 45" fovy="45" mode="fixed" name="cam_16" pos="5 -5 9"/>
  <camera euler="45 0 -180" fovy="45" mode="fixed" name="cam_17" pos="0 8 9"/>
 </worldbody>
 <sensor>
  <velocimeter name="velo_collapse" site="sensor_site_velo_collapse"/>
 </sensor>
</world>