<?xml version="1.0" encoding="utf-8"?>
<world>
 <worldbody>
  <geom euler="0 0 0" material="mat_floor_001" name="floor" pos="0 0 0" size="3 3 0.5" type="plane"/>
  <body pos="-0.39827244767811515 0.5438777477417042 0.050383426760527594">
   <freejoint/>
   <geom condim="6" density="20" euler="0 0 0" friction="1 0.01 0.1" name="shape_3" pos="0 0 0" rgba="0 0 1 1" size="0.050383426760527594" type="sphere"/>
   <body>
    <site name="sensor_site_velo_collapse" pos="0 0 0" size="0.01"/>
   </body>
  </body>
  <body pos="0.011299432359034522 -0.017439742211910025 0.05131328077648909">
   <freejoint/>
   <geom condim="6" density="20" euler="0 0 0" friction="1 0.01 0.1" name="shape_2" pos="0 0 0" rgba="1 0 1 1" size="0.06304561281729211 0.05131328077648909" type="cylinder"/>
  </body>
  <body pos="-0.42390970400449135 0.40362885655293523 0.05140966006458447">
   <freejoint/>
   <geom condim="6" density="20" euler="0 0 0" friction="1 0.01 0.1" name="shape_1" pos="0 0 0" rgba="0 1 1 1" size="0.07101954602051724 0.05140966006458447" type="cylinder"/>
  </body>
  <light castshadow="false" dir="0 0 -20" directional="true" mode="fixed" name="light_0" pos="0 0 20"/>
  <light castshadow="false" dir="9 9 -20" directional="true" mode="fixed" name="light_1" pos="-9 -9 20"/>
  <light castshadow="false" dir="9 -9 -20" directional="true" mode="fixed" name="light_2" pos="-9 9 20"/>
  <light castshadow="false" dir="-9 -9 -20" directional="true" mode="fixed" name="light_3" pos="9 9 20"/>
  <light castshadow="false" dir="-9 9 -20" directional="true" mode="fixed" name="light_4" pos="9 -9 20"/>
  <camera euler="54.016525049192644 -3.0802463479195204e-08 160.3708677750489" fovy="45" mode="fixed" name="cam_1" pos="0.5436608909589584 1.524324110255273 1.175103758200178"/>
  <camera euler="81.18102011473418 -1.3722986617485925e-08 2.996517424541239" fovy="45" mode="fixed" name="cam_2" pos="0.10331447809550325 -1.9736530450830523 0.3066264441470255"/>
  <camera euler="49.65517022502705 1.2722218725854067e-14 89.99999999999999" fovy="45" mode="fixed" name="cam_3" pos="1.524324110255273 -4.898587196589413e-16 1.2947725695636554"/>
 </worldbody>
 <sensor>
  <velocimeter name="velo_collapse" site="sensor_site_velo_collapse"/>
 </sensor>
</world>