<?xml version="1.0" encoding="utf-8"?>
<world>
 <worldbody>
  <geom euler="0 0 0" material="mat_floor_001" name="floor" pos="0 0 0" size="20 20 0.5" type="plane"/>
  <body pos="0.65296133108528 0.8186656543705637 0.2637780336621297">
   <freejoint/>
   <geom condim="6" density="20" euler="0 0 0" friction="1 0.01 0.1" name="shape_3" pos="0 0 0" rgba="0 1 0 1" size="0.2637780336621297" type="sphere"/>
   <body>
    <site name="sensor_site_velo_collapse" pos="0 0 0" size="0.01"/>
   </body>
  </body>
  <body pos="-0.8332917307539849 -1.7965097227517823 0.3111361672639234">
   <freejoint/>
   <geom condim="6" density="20" euler="0 0 0" friction="1 0.01 0.1" name="shape_2" pos="0 0 0" rgba="1 1 0 1" size="0.4854301231185083 0.3111361672639234" type="cylinder"/>
  </body>
  <body pos="1.2138348266285863 0.9732270962253691 0.36258726399858815">
   <freejoint/>
   <geom condim="6" density="20" euler="0 0 0" friction="1 0.01 0.1" name="shape_1" pos="0 0 0" rgba="1 0 1 1" size="0.297117187383233 0.36258726399858815" type="cylinder"/>
  </body>
  <light castshadow="false" dir="0 0 -20" directional="true" mode="fixed" name="light_0" pos="0 0 20"/>
  <light castshadow="false" dir="9 9 -20" directional="true" mode="fixed" name="light_1" pos="-9 -9 20"/>
  <light castshadow="false" dir="9 -9 -20" directional="true" mode="fixed" name="light_2" pos="-9 9 20"/>
  <light castshadow="false" dir="-9 -9 -20" directional="true" mode="fixed" name="light_3" pos="9 9 20"/>
  <light castshadow="false" dir="-9 9 -20" directional="true" mode="fixed" name="light_4" pos="9 -9 20"/>
  <camera euler="39.176533549090664 1.6880762166320802e-07 -18.771563754071355" fovy="45" mode="fixed" name="cam_1" pos="-1.8295401491489511 -5.382994774420946 6.976829516421397"/>
  <camera euler="45.38079270757491 3.55550658341782e-07 -39.965976180605736" fovy="45" mode="fixed" name="cam_2" pos="-4.114856803571153 -4.909814110894939 6.321525044050772"/>
  <camera euler="40.54625063921782 -3.9464564209755106e-08 4.303996595111182" fovy="45" mode="fixed" name="cam_3" pos="0.43907409050521756 -5.834055557770093 6.838933373845581"/>
 </worldbody>
 <sensor>
  <velocimeter name="velo_collapse" site="sensor_site_velo_collapse"/>
 </sensor>
</world>