<?xml version="1.0" encoding="utf-8"?>
<world>
 <worldbody>
  <geom euler="0 0 0" material="mat_floor_001" name="floor" pos="0 0 0" size="3 3 0.5" type="plane"/>
  <body euler="90 0 156" pos="0.17021575711992165 0.05311250443477711 0.06943852661362525">
   <freejoint/>
   <geom condim="6" density="20" euler="0 0 0" friction="1 0.01 0.1" name="shape_4" pos="0 0 0" rgba="1 0 1 1" size="0.06943852661362525 0.0707647677409585" type="cylinder"/>
   <body>
    <site name="sensor_site_velo_collapse" pos="0 0 0" size="0.01"/>
   </body>
  </body>
  <body pos="-0.5338521200287402 0.2463321090307098 0.057633225380330805">
   <freejoint/>
   <geom condim="6" density="20" euler="0 0 0" friction="1 0.01 0.1" name="shape_3" pos="0 0 0" rgba="1 0 0 1" size="0.057026397384665584 0.057633225380330805" type="cylinder"/>
  </body>
  <body pos="0.3505573118588796 -0.26893875022723135 0.07086334169846416">
   <freejoint/>
   <geom condim="6" density="20" euler="0 0 0" friction="1 0.01 0.1" name="shape_2" pos="0 0 0" rgba="0 1 0 1" size="0.06351183158799831 0.07086334169846416" type="cylinder"/>
  </body>
  <body pos="0.5167374206926055 -0.5019458560925737 0.05160986498653388">
   <freejoint/>
   <geom condim="6" density="20" euler="0 0 0" friction="1 0.01 0.1" name="shape_1" pos="0 0 0" rgba="0 0 1 1" size="0.05104955197137858 0.05160986498653388" type="cylinder"/>
  </body>
  <light castshadow="false" dir="0 0 -20" directional="true" mode="fixed" name="light_0" pos="0 0 20"/>
  <light castshadow="false" dir="9 9 -20" directional="true" mode="fixed" name="light_1" pos="-9 -9 20"/>
  <light castshadow="false" dir="9 -9 -20" directional="true" mode="fixed" name="light_2" pos="-9 9 20"/>
  <light castshadow="false" dir="-9 -9 -20" directional="true" mode="fixed" name="light_3" pos="9 9 20"/>
  <light castshadow="false" dir="-9 9 -20" directional="true" mode="fixed" name="light_4" pos="9 -9 20"/>
  <camera euler="77.70310577571503 -6.721499667772099e-07 -128.27121559089125" fovy="45" mode="fixed" name="cam_1" pos="-1.5341509350105564 1.2103484303875303 0.42595491036572963"/>
  <camera euler="35.70786415861859 -3.8037546013044743e-07 123.16654628719684" fovy="45" mode="fixed" name="cam_2" pos="0.9771324953386606 0.6386030602719605 1.624006840491914"/>
  <camera euler="24.827585573480242 0.0 -89.99999999999997" fovy="45" mode="fixed" name="cam_3" pos="-0.8397782031205299 -4.898587196589413e-16 1.8151508393419138"/>
 </worldbody>
 <sensor>
  <velocimeter name="velo_collapse" site="sensor_site_velo_collapse"/>
 </sensor>
</world>