<?xml version="1.0" encoding="utf-8"?>
<world>
 <worldbody>
  <geom euler="0 0 0" material="mat_floor_001" name="floor" pos="0 0 0" size="3 3 0.5" type="plane"/>
  <body pos="0.1487935679757132 0.1211235424817041 0.06459983044836831">
   <freejoint/>
   <geom condim="6" density="20" euler="0 0 0" friction="1 0.01 0.1" name="shape_4" pos="0 0 0" rgba="0 1 1 1" size="0.06459983044836831" type="sphere"/>
   <body>
    <site name="sensor_site_velo_collapse" pos="0 0 0" size="0.01"/>
   </body>
  </body>
  <body pos="-0.1956274002829554 -0.46861895850204205 0.06532383876622228">
   <freejoint/>
   <geom condim="6" density="20" euler="0 0 0" friction="1 0.01 0.1" name="shape_3" pos="0 0 0" rgba="1 1 0 1" size="0.05675463816979281 0.06532383876622228" type="cylinder"/>
  </body>
  <body pos="0.42097284099251386 -0.47827754291344265 0.055090425398086444">
   <freejoint/>
   <geom condim="6" density="20" euler="0 0 0" friction="1 0.01 0.1" name="shape_2" pos="0 0 0" rgba="0 1 0 1" size="0.06196490034439928 0.055090425398086444" type="cylinder"/>
  </body>
  <body pos="0.28426722301177865 -0.3068930377055204 0.06822344522219549">
   <freejoint/>
   <geom condim="6" density="20" euler="0 0 0" friction="1 0.01 0.1" name="shape_1" pos="0 0 0" rgba="1 0 1 1" size="0.05099076895948278 0.06822344522219549" type="cylinder"/>
  </body>
  <light castshadow="false" dir="0 0 -20" directional="true" mode="fixed" name="light_0" pos="0 0 20"/>
  <light castshadow="false" dir="9 9 -20" directional="true" mode="fixed" name="light_1" pos="-9 -9 20"/>
  <light castshadow="false" dir="9 -9 -20" directional="true" mode="fixed" name="light_2" pos="-9 9 20"/>
  <light castshadow="false" dir="-9 -9 -20" directional="true" mode="fixed" name="light_3" pos="9 9 20"/>
  <light castshadow="false" dir="-9 9 -20" directional="true" mode="fixed" name="light_4" pos="9 -9 20"/>
  <camera euler="74.48276011340046 0.0 -3.8963596351940015e-15" fovy="45" mode="fixed" name="cam_1" pos="-1.31051089384408e-16 -1.9270999850384458 0.535056677058442"/>
  <camera euler="42.7599833833177 7.13279882140398e-07 -40.59185762689752" fovy="45" mode="fixed" name="cam_2" pos="-0.8835120444460234 -1.0311077143540437 1.4684084406997897"/>
  <camera euler="49.65517022502705 0.0 -180.0" fovy="45" mode="fixed" name="cam_3" pos="-3.171278165879849e-16 1.524324110255273 1.2947725695636554"/>
 </worldbody>
 <sensor>
  <velocimeter name="velo_collapse" site="sensor_site_velo_collapse"/>
 </sensor>
</world>