<?xml version="1.0" encoding="utf-8"?>
<world>
 <worldbody>
  <geom euler="0 0 0" material="mat_floor_001" name="floor" pos="0 0 0" size="20 20 0.5" type="plane"/>
  <body pos="1.6481759613467482 -0.9317434207883246 0.3760712716518907">
   <freejoint/>
   <geom condim="6" density="20" euler="0 0 0" friction="1 0.01 0.1" name="shape_4" pos="0 0 0" rgba="0 1 1 1" size="0.3305646538506161 0.3760712716518907" type="cylinder"/>
   <body>
    <site name="sensor_site_velo_collapse" pos="0 0 0" size="0.01"/>
   </body>
  </body>
  <body pos="-0.9770420825061072 1.7887034119058578 0.49375251021879296">
   <freejoint/>
   <geom condim="6" density="20" euler="0 0 0" friction="1 0.01 0.1" name="shape_3" pos="0 0 0" rgba="0 1 0 1" size="0.46495979657295994 0.49375251021879296" type="cylinder"/>
  </body>
  <body euler="0 0 153" pos="0.7318452221053993 -1.0444310924061257 0.4137291443882508">
   <freejoint/>
   <geom condim="6" density="20" euler="0 0 0" friction="1 0.01 0.1" name="shape_2" pos="0 0 0" rgba="1 0 0 1" size="0.32724554378823634 0.32660350849467834 0.4137291443882508" type="box"/>
  </body>
  <body euler="0 0 243" pos="-1.079448284949724 1.8631387580229495 0.4327245324900536">
   <freejoint/>
   <geom condim="6" density="20" euler="0 0 0" friction="1 0.01 0.1" name="shape_1" pos="0 0 0" rgba="0 0 1 1" size="0.3031124717238258 0.3161437798770737 0.4327245324900536" type="box"/>
  </body>
  <light castshadow="false" dir="0 0 -20" directional="true" mode="fixed" name="light_0" pos="0 0 20"/>
  <light castshadow="false" dir="9 9 -20" directional="true" mode="fixed" name="light_1" pos="-9 -9 20"/>
  <light castshadow="false" dir="9 -9 -20" directional="true" mode="fixed" name="light_2" pos="-9 9 20"/>
  <light castshadow="false" dir="-9 -9 -20" directional="true" mode="fixed" name="light_3" pos="9 9 20"/>
  <light castshadow="false" dir="-9 9 -20" directional="true" mode="fixed" name="light_4" pos="9 -9 20"/>
  <camera euler="36.73469132288695 0.0 -89.99999999999997" fovy="45" mode="fixed" name="cam_1" pos="-5.382994774420946 -2.204364238465236e-15 7.212722596811608"/>
  <camera euler="40.54624907208919 -1.5235384514620805e-06 -95.65626607245908" fovy="45" mode="fixed" name="cam_2" pos="-5.822068864926161 0.5766319798264151 6.838933373845579"/>
  <camera euler="30.775959409547447 6.488002680831511e-07 -42.827951185239506" fovy="45" mode="fixed" name="cam_3" pos="-3.130571477715687 -3.377403043914364 7.732572075439778"/>
 </worldbody>
 <sensor>
  <velocimeter name="velo_collapse" site="sensor_site_velo_collapse"/>
 </sensor>
</world>