<?xml version="1.0" encoding="utf-8"?>
<world>
 <worldbody>
  <geom euler="0 0 0" material="mat_floor_001" name="floor" pos="0 0 0" size="20 20 0.5" type="plane"/>
  <body euler="0 0 293" pos="1.6448174965803095 -1.8726667911292805 0.3261644793326111">
   <freejoint/>
   <geom condim="6" density="20" euler="0 0 0" friction="1 0.01 0.1" name="shape_3" pos="0 0 0" rgba="0 1 1 1" size="0.33860517125402323 0.382964695449826 0.3261644793326111" type="box"/>
   <body>
    <site name="sensor_site_velo_collapse" pos="0 0 0" size="0.01"/>
   </body>
  </body>
  <body euler="0 0 320" pos="0.07145592315830385 0.9443937714064221 0.40177469543851685">
   <freejoint/>
   <geom condim="6" density="20" euler="0 0 0" friction="1 0.01 0.1" name="shape_2" pos="0 0 0" rgba="1 0 1 1" size="0.39701942298190995 0.3661870048381603 0.40177469543851685" type="box"/>
  </body>
  <body euler="0 0 149" pos="1.3415315204275493 -1.1537552994227278 0.2913609178468045">
   <freejoint/>
   <geom condim="6" density="20" euler="0 0 0" friction="1 0.01 0.1" name="shape_1" pos="0 0 0" rgba="0 0 1 1" size="0.2960110471764519 0.30589557631125586 0.2913609178468045" type="box"/>
  </body>
  <light castshadow="false" dir="0 0 -20" directional="true" mode="fixed" name="light_0" pos="0 0 20"/>
  <light castshadow="false" dir="9 9 -20" directional="true" mode="fixed" name="light_1" pos="-9 -9 20"/>
  <light castshadow="false" dir="9 -9 -20" directional="true" mode="fixed" name="light_2" pos="-9 9 20"/>
  <light castshadow="false" dir="-9 -9 -20" directional="true" mode="fixed" name="light_3" pos="9 9 20"/>
  <light castshadow="false" dir="-9 9 -20" directional="true" mode="fixed" name="light_4" pos="9 -9 20"/>
  <camera euler="43.72590904961552 -5.212189962010732e-08 159.6882670228756" fovy="45" mode="fixed" name="cam_1" pos="2.1594409115668736 5.834055557770096 6.503891965454461"/>
  <camera euler="37.36041748889701 -1.1695345350285505e-06 -102.16518679639094" fovy="45" mode="fixed" name="cam_2" pos="-5.3388004617334115 1.150894455160554 7.153506243995024"/>
  <camera euler="46.6826200670547 7.1042507986941e-07 126.60898380055735" fovy="45" mode="fixed" name="cam_3" pos="5.256302431163937 3.904953652058024 6.174351927726406"/>
 </worldbody>
 <sensor>
  <velocimeter name="velo_collapse" site="sensor_site_velo_collapse"/>
 </sensor>
</world>