<?xml version="1.0" encoding="utf-8"?>
<world>
 <worldbody>
  <geom euler="0 0 0" material="mat_floor_001" name="floor" pos="0 0 0" size="20 20 0.5" type="plane"/>
  <body euler="0 0 309" pos="-0.2438167647473044 0.92817052428589 0.4788563871916179">
   <freejoint/>
   <geom condim="6" density="20" euler="0 0 0" friction="1 0.01 0.1" name="shape_4" pos="0 0 0" rgba="0 1 1 1" size="0.3116585065966929 0.4482979246042679 0.4788563871916179" type="box"/>
   <body>
    <site name="sensor_site_velo_collapse" pos="0 0 0" size="0.01"/>
   </body>
  </body>
  <body euler="0 0 107" pos="-0.4038995055942016 1.2790458668228895 0.43869143545733835">
   <freejoint/>
   <geom condim="6" density="20" euler="0 0 0" friction="1 0.01 0.1" name="shape_3" pos="0 0 0" rgba="0 0 1 1" size="0.47547802270954764 0.27385312873398326 0.43869143545733835" type="box"/>
  </body>
  <body pos="-1.8487742206873499 -0.311061475117977 0.41482988216369976">
   <freejoint/>
   <geom condim="6" density="20" euler="0 0 0" friction="1 0.01 0.1" name="shape_2" pos="0 0 0" rgba="1 1 0 1" size="0.39823190287688215 0.41482988216369976" type="cylinder"/>
  </body>
  <body euler="0 0 280" pos="-0.8220099543961514 -1.808500021316359 0.35262311261509305">
   <freejoint/>
   <geom condim="6" density="20" euler="0 0 0" friction="1 0.01 0.1" name="shape_1" pos="0 0 0" rgba="1 0 0 1" size="0.4397055756140883 0.2716187953635213 0.35262311261509305" type="box"/>
  </body>
  <light castshadow="false" dir="0 0 -20" directional="true" mode="fixed" name="light_0" pos="0 0 20"/>
  <light castshadow="false" dir="9 9 -20" directional="true" mode="fixed" name="light_1" pos="-9 -9 20"/>
  <light castshadow="false" dir="9 -9 -20" directional="true" mode="fixed" name="light_2" pos="-9 9 20"/>
  <light castshadow="false" dir="-9 -9 -20" directional="true" mode="fixed" name="light_3" pos="9 9 20"/>
  <light castshadow="false" dir="-9 9 -20" directional="true" mode="fixed" name="light_4" pos="9 -9 20"/>
  <camera euler="42.02577728606918 2.372224596945174e-07 -55.906319365614785" fovy="45" mode="fixed" name="cam_1" pos="-4.989588061116844 -3.377403043914364 6.685593441072996"/>
  <camera euler="43.72590841197749 1.3511841042180415e-07 -117.12154616125349" fovy="45" mode="fixed" name="cam_2" pos="-5.536843955481241 2.835973962212588 6.50389196545446"/>
  <camera euler="30.775959409547447 -6.488002680831511e-07 -137.1720488147605" fovy="45" mode="fixed" name="cam_3" pos="-3.1305714777156854 3.3774030439143674 7.732572075439775"/>
 </worldbody>
 <sensor>
  <velocimeter name="velo_collapse" site="sensor_site_velo_collapse"/>
 </sensor>
</world>