<?xml version="1.0" encoding="utf-8"?>
<world>
 <worldbody>
  <geom euler="0 0 0" material="mat_floor_001" name="floor" pos="0 0 0" size="20 20 0.5" type="plane"/>
  <body euler="0 0 224" pos="1.6715949152057932 1.96181174919279 1.508429524946333">
   <freejoint/>
   <geom condim="6" density="20" euler="0 0 0" friction="1 0.01 0.1" name="shape_3" pos="0 0 0" rgba="1 1 0 1" size="0.34638826256402644 0.34635644044773695 0.38123020146720277" type="box"/>
   <body>
    <site name="sensor_site_velo_collapse" pos="0 0 0" size="0.01"/>
   </body>
  </body>
  <body euler="0 0 255" pos="1.6501988963361678 1.809591389097065 0.8321657504854671">
   <freejoint/>
   <geom condim="6" density="20" euler="0 0 0" friction="1 0.01 0.1" name="shape_2" pos="0 0 0" rgba="0 1 0 1" size="0.32911171718498444 0.3573026869634227 0.2950335729936633" type="box"/>
  </body>
  <body euler="0 0 201" pos="1.558048416948003 1.9825056899810458 0.26856608874590204">
   <freejoint/>
   <geom condim="6" density="20" euler="0 0 0" friction="1 0.01 0.1" name="shape_1" pos="0 0 0" rgba="1 0 1 1" size="0.380648317830378 0.28627156526195385 0.26856608874590193" type="box"/>
  </body>
  <light castshadow="false" dir="0 0 -20" directional="true" mode="fixed" name="light_0" pos="0 0 20"/>
  <light castshadow="false" dir="9 9 -20" directional="true" mode="fixed" name="light_1" pos="-9 -9 20"/>
  <light castshadow="false" dir="9 -9 -20" directional="true" mode="fixed" name="light_2" pos="-9 9 20"/>
  <light castshadow="false" dir="-9 -9 -20" directional="true" mode="fixed" name="light_3" pos="9 9 20"/>
  <light castshadow="false" dir="-9 9 -20" directional="true" mode="fixed" name="light_4" pos="9 -9 20"/>
  <camera euler="43.72590841197749 1.3511841042180415e-07 -117.12154616125349" fovy="45" mode="fixed" name="cam_1" pos="-5.536843955481241 2.835973962212588 6.50389196545446"/>
  <camera euler="47.86192307402141 9.470610452806655e-09 -3.330107724588934" fovy="45" mode="fixed" name="cam_2" pos="-0.38767019339044445 -6.66250197367784 6.038276183804074"/>
  <camera euler="35.73323524660104 1.5690923021094663e-07 42.01786798651411" fovy="45" mode="fixed" name="cam_3" pos="3.5182416711061335 -3.904953652058022 7.305704108364302"/>
 </worldbody>
 <sensor>
  <velocimeter name="velo_collapse" site="sensor_site_velo_collapse"/>
 </sensor>
</world>