<?xml version="1.0" encoding="utf-8"?>
<world>
 <worldbody>
  <geom euler="0 0 0" material="mat_floor_001" name="floor" pos="0 0 0" size="20 20 0.5" type="plane"/>
  <body euler="90 0 308" pos="1.6458042004186488 0.719056488713536 2.182929843093014">
   <freejoint/>
   <geom condim="6" density="20" euler="0 0 0" friction="1 0.01 0.1" name="shape_3" pos="0 0 0" rgba="1 1 0 1" size="0.4216498392993399 0.28102141629698285" type="cylinder"/>
   <body>
    <site name="sensor_site_velo_collapse" pos="0 0 0" size="0.01"/>
   </body>
  </body>
  <body pos="1.4632743232092293 0.6590971842457427 1.3217110139304928">
   <freejoint/>
   <geom condim="6" density="20" euler="0 0 0" friction="1 0.01 0.1" name="shape_2" pos="0 0 0" rgba="1 0 1 1" size="0.2650597544188388 0.4395689898631812" type="cylinder"/>
  </body>
  <body pos="1.6384036034647995 0.6896222792113029 0.44107101203365584">
   <freejoint/>
   <geom condim="6" density="20" euler="0 0 0" friction="1 0.01 0.1" name="shape_1" pos="0 0 0" rgba="1 0 0 1" size="0.3805897812187562 0.44107101203365584" type="cylinder"/>
  </body>
  <light castshadow="false" dir="0 0 -20" directional="true" mode="fixed" name="light_0" pos="0 0 20"/>
  <light castshadow="false" dir="9 9 -20" directional="true" mode="fixed" name="light_1" pos="-9 -9 20"/>
  <light castshadow="false" dir="9 -9 -20" directional="true" mode="fixed" name="light_2" pos="-9 9 20"/>
  <light castshadow="false" dir="-9 -9 -20" directional="true" mode="fixed" name="light_3" pos="9 9 20"/>
  <light castshadow="false" dir="-9 9 -20" directional="true" mode="fixed" name="light_4" pos="9 -9 20"/>
  <camera euler="36.13402074003422 -5.015134243944106e-08 -129.52354400524652" fovy="45" mode="fixed" name="cam_1" pos="-4.09368889868641 3.3774030439143674 7.268759170568908"/>
  <camera euler="33.24163629866533 -5.0736971611829573e-08 -174.3785368502671" fovy="45" mode="fixed" name="cam_2" pos="-0.48326840319275044 4.909814110894935 7.52729546696106"/>
  <camera euler="46.68261975680784 -1.8851105613712469e-07 152.99367599754234" fovy="45" mode="fixed" name="cam_3" pos="2.973411175978372 5.834055557770096 6.174351927726405"/>
 </worldbody>
 <sensor>
  <velocimeter name="velo_collapse" site="sensor_site_velo_collapse"/>
 </sensor>
</world>